{
  "templates": {
    "type": "JSON",
    "content": [
      {
        "id": "145718333",
        "Flight": "WS2903",
        "PickupDate": "2026-02-27",
        "PickupTime": "10:45",
        "HotelName": "Royalton Splash Punta Cana Resort and Spa",
        "HotelNumber": 15810
      },
      {
        "id": "461-2763187",
        "Flight": "CM109",
        "PickupDate": "2026-02-27",
        "PickupTime": "08:25",
        "HotelName": "Royalton Splash Punta Cana Resort and Spa",
        "HotelNumber": 15810
      },
      {
        "id": "10888SG775697",
        "Flight": "DL1755",
        "PickupDate": "2026-02-27",
        "PickupTime": "12:10",
        "HotelName": "Royalton Splash Punta Cana Resort and Spa",
        "HotelNumber": 15810
      },
      {
        "id": "149354313",
        "Flight": "WS2913",
        "PickupDate": "2026-02-27",
        "PickupTime": "12:15",
        "HotelName": "Royalton Splash Punta Cana Resort and Spa",
        "HotelNumber": 15810
      },
      {
        "id": "149863923",
        "Flight": "WS2743",
        "PickupDate": "2026-02-27",
        "PickupTime": "14:45",
        "HotelName": "Royalton Splash Punta Cana Resort and Spa",
        "HotelNumber": 15810
      },
      {
        "id": "149980913",
        "Flight": "WS2913",
        "PickupDate": "2026-02-27",
        "PickupTime": "12:15",
        "HotelName": "Royalton Splash Punta Cana Resort and Spa",
        "HotelNumber": 15810
      },
      {
        "id": "149864303",
        "Flight": "WS2743",
        "PickupDate": "2026-02-27",
        "PickupTime": "14:45",
        "HotelName": "Royalton Splash Punta Cana Resort and Spa",
        "HotelNumber": 15810
      },
      {
        "id": "145972483",
        "Flight": "WS2655",
        "PickupDate": "2026-02-27",
        "PickupTime": "11:05",
        "HotelName": "Royalton Splash Punta Cana Resort and Spa",
        "HotelNumber": 15810
      },
      {
        "id": "10888SF719586",
        "Flight": "UPP000",
        "PickupDate": "2026-02-27",
        "PickupTime": "⚠️",
        "HotelName": "Royalton Splash Punta Cana Resort and Spa",
        "HotelNumber": 15810
      },
      {
        "id": "149872743",
        "Flight": "WS2655",
        "PickupDate": "2026-02-27",
        "PickupTime": "07:35",
        "HotelName": "Royalton Splash Punta Cana Resort and Spa",
        "HotelNumber": 15810
      },
      {
        "id": "147623492",
        "Flight": "WS2655",
        "PickupDate": "2026-02-27",
        "PickupTime": "07:35",
        "HotelName": "Royalton Splash Punta Cana Resort and Spa",
        "HotelNumber": 15810
      },
      {
        "id": "10888SF729026",
        "Flight": "TBA000",
        "PickupDate": "2026-02-27",
        "PickupTime": "⚠️",
        "HotelName": "Royalton Splash Punta Cana Resort and Spa",
        "HotelNumber": 15810
      },
      {
        "id": "149695243",
        "Flight": "WS2903",
        "PickupDate": "2026-02-27",
        "PickupTime": "10:45",
        "HotelName": "Royalton Splash Punta Cana Resort and Spa",
        "HotelNumber": 15810
      },
      {
        "id": "145646332",
        "Flight": "WS2703",
        "PickupDate": "2026-02-27",
        "PickupTime": "10:45",
        "HotelName": "Royalton Splash Punta Cana Resort and Spa",
        "HotelNumber": 15810
      },
      {
        "id": "10888SF732524",
        "Flight": "B6496",
        "PickupDate": "2026-02-27",
        "PickupTime": "13:35",
        "HotelName": "Royalton Splash Punta Cana Resort and Spa",
        "HotelNumber": 15810
      },
      {
        "id": "149178242",
        "Flight": "WS2703",
        "PickupDate": "2026-02-27",
        "PickupTime": "10:45",
        "HotelName": "Royalton Splash Punta Cana Resort and Spa",
        "HotelNumber": 15810
      },
      {
        "id": "149790503",
        "Flight": "WS2903",
        "PickupDate": "2026-02-27",
        "PickupTime": "10:45",
        "HotelName": "Royalton Splash Punta Cana Resort and Spa",
        "HotelNumber": 15810
      },
      {
        "id": "10888SF733993",
        "Flight": "TBA000",
        "PickupDate": "2026-02-27",
        "PickupTime": "⚠️",
        "HotelName": "Royalton Splash Punta Cana Resort and Spa",
        "HotelNumber": 15810
      },
      {
        "id": "149873703",
        "Flight": "WS2655",
        "PickupDate": "2026-02-27",
        "PickupTime": "07:35",
        "HotelName": "Royalton Splash Punta Cana Resort and Spa",
        "HotelNumber": 15810
      },
      {
        "id": "149322733",
        "Flight": "WS2913",
        "PickupDate": "2026-02-27",
        "PickupTime": "12:15",
        "HotelName": "Royalton Splash Punta Cana Resort and Spa",
        "HotelNumber": 15810
      },
      {
        "id": "10888SF740600",
        "Flight": "AA2399",
        "PickupDate": "2026-02-27",
        "PickupTime": "09:25",
        "HotelName": "Royalton Splash Punta Cana Resort and Spa",
        "HotelNumber": 15810
      },
      {
        "id": "149177842",
        "Flight": "WS2703",
        "PickupDate": "2026-02-27",
        "PickupTime": "10:45",
        "HotelName": "Royalton Splash Punta Cana Resort and Spa",
        "HotelNumber": 15810
      },
      {
        "id": "10888SF725999",
        "Flight": "TBA000",
        "PickupDate": "2026-02-27",
        "PickupTime": "⚠️",
        "HotelName": "Royalton Splash Punta Cana Resort and Spa",
        "HotelNumber": 15810
      },
      {
        "id": "149863983",
        "Flight": "WS2743",
        "PickupDate": "2026-02-27",
        "PickupTime": "14:45",
        "HotelName": "Royalton Splash Punta Cana Resort and Spa",
        "HotelNumber": 15810
      },
      {
        "id": "143633561",
        "Flight": "WS2879",
        "PickupDate": "2026-02-27",
        "PickupTime": "17:25",
        "HotelName": "Royalton Splash Punta Cana Resort and Spa",
        "HotelNumber": 15810
      }
    ],
    "source": {
      "data_source": "Google Sheets (Private)",
      "update_frequency": "Automated"
    }
  }
}